{"config_name": "neat_grid_DYDXUSDT_294days",
 "logging_level": 0,
 "long": {"auto_unstuck_ema_dist": 0,
          "auto_unstuck_wallet_exposure_threshold": 0,
          "backwards_tp": true,
          "ema_span_0": 881.8255687321274,
          "ema_span_1": 980.7957992473158,
          "enabled": false,
          "eprice_exp_base": 1.1601813064149127,
          "eqty_exp_base": 1.211657342063258,
          "grid_span": 0.03866197461799427,
          "initial_eprice_ema_dist": -0.08342841984003907,
          "initial_qty_pct": 0.03103140074100215,
          "markup_range": 0.028554044667328186,
          "max_n_entry_orders": 8,
          "min_markup": 0.002,
          "n_close_orders": 6,
          "wallet_exposure_limit": 1},
 "short": {"auto_unstuck_ema_dist": 0,
           "auto_unstuck_wallet_exposure_threshold": 0,
           "backwards_tp": true,
           "ema_span_0": 45.13509798163823,
           "ema_span_1": 10,
           "enabled": true,
           "eprice_exp_base": 1.2800592113315974,
           "eqty_exp_base": 2.8010120831288856,
           "grid_span": 0.19007955460712653,
           "initial_eprice_ema_dist": -0.029342766470787558,
           "initial_qty_pct": 0.04132916988419283,
           "markup_range": 0.01957314365775212,
           "max_n_entry_orders": 10,
           "min_markup": 0.002,
           "n_close_orders": 6,
           "wallet_exposure_limit": 1}}